<?xml version="1.0" encoding="UTF-8"?><!-- Generated by Sonar -->
<profile>
	<name>Matrix</name>
	<language>js</language>
	<rules>
		<rule>
			<repositoryKey>javascript</repositoryKey>
			<key>CommentedCode</key>
			<priority>MAJOR</priority>
		</rule>
		<rule>
			<repositoryKey>javascript</repositoryKey>
			<key>FunctionComplexity</key>
			<priority>MAJOR</priority>
			<parameters>
				<parameter>
					<key>maximumFunctionComplexityThreshold</key>
					<value>10</value>
				</parameter>
			</parameters>
		</rule>
		<rule>
			<repositoryKey>javascript</repositoryKey>
			<key>DebuggerStatement</key>
			<priority>MAJOR</priority>
		</rule>
		<rule>
			<repositoryKey>javascript</repositoryKey>
			<key>WithStatement</key>
			<priority>MAJOR</priority>
		</rule>
		<rule>
			<repositoryKey>javascript</repositoryKey>
			<key>EqEqEq</key>
			<priority>MAJOR</priority>
		</rule>
		<rule>
			<repositoryKey>javascript</repositoryKey>
			<key>Eval</key>
			<priority>MAJOR</priority>
		</rule>
		<rule>
			<repositoryKey>javascript</repositoryKey>
			<key>OneStatementPerLine</key>
			<priority>MAJOR</priority>
		</rule>
		<rule>
			<repositoryKey>javascript</repositoryKey>
			<key>Semicolon</key>
			<priority>MAJOR</priority>
		</rule>
		<rule>
			<repositoryKey>javascript</repositoryKey>
			<key>CurlyBraces</key>
			<priority>MAJOR</priority>
		</rule>
		<rule>
			<repositoryKey>javascript</repositoryKey>
			<key>MultilineStringLiterals</key>
			<priority>MAJOR</priority>
		</rule>
		<rule>
			<repositoryKey>javascript</repositoryKey>
			<key>ArrayAndObjectConstructors</key>
			<priority>MAJOR</priority>
		</rule>
		<rule>
			<repositoryKey>javascript</repositoryKey>
			<key>BitwiseOperators</key>
			<priority>MAJOR</priority>
		</rule>
		<rule>
			<repositoryKey>javascript</repositoryKey>
			<key>PrimitiveWrappers</key>
			<priority>MAJOR</priority>
		</rule>
		<rule>
			<repositoryKey>javascript</repositoryKey>
			<key>ForIn</key>
			<priority>MAJOR</priority>
		</rule>
		<rule>
			<repositoryKey>javascript</repositoryKey>
			<key>FunctionDeclarationsWithinBlocks</key>
			<priority>MAJOR</priority>
		</rule>
		<rule>
			<repositoryKey>javascript</repositoryKey>
			<key>TrailingComma</key>
			<priority>BLOCKER</priority>
		</rule>
		<rule>
			<repositoryKey>javascript</repositoryKey>
			<key>AssignmentWithinCondition</key>
			<priority>MAJOR</priority>
		</rule>
		<rule>
			<repositoryKey>javascript</repositoryKey>
			<key>LabelPlacement</key>
			<priority>MAJOR</priority>
		</rule>
		<rule>
			<repositoryKey>javascript</repositoryKey>
			<key>UnreachableCode</key>
			<priority>MAJOR</priority>
		</rule>
		<rule>
			<repositoryKey>javascript</repositoryKey>
			<key>SwitchWithoutDefault</key>
			<priority>MAJOR</priority>
		</rule>
		<rule>
			<repositoryKey>javascript</repositoryKey>
			<key>NonEmptyCaseWithoutBreak</key>
			<priority>MAJOR</priority>
		</rule>
		<rule>
			<repositoryKey>javascript</repositoryKey>
			<key>HtmlComments</key>
			<priority>MAJOR</priority>
		</rule>
		<rule>
			<repositoryKey>javascript</repositoryKey>
			<key>NestedIfDepth</key>
			<priority>MINOR</priority>
			<parameters>
				<parameter>
					<key>maximumNestingLevel</key>
					<value>3</value>
				</parameter>
			</parameters>
		</rule>
		<rule>
			<repositoryKey>javascript</repositoryKey>
			<key>LineLength</key>
			<priority>MINOR</priority>
		</rule>
		<rule>
			<repositoryKey>javascript</repositoryKey>
			<key>Parentheses</key>
			<priority>MINOR</priority>
		</rule>
		<rule>
			<repositoryKey>javascript</repositoryKey>
			<key>ContinueStatement</key>
			<priority>MAJOR</priority>
		</rule>
		<rule>
			<repositoryKey>javascript</repositoryKey>
			<key>ConditionalOperator</key>
			<priority>MINOR</priority>
		</rule>
		<rule>
			<repositoryKey>javascript</repositoryKey>
			<key>ParsingError</key>
			<priority>MAJOR</priority>
		</rule>
		<rule>
			<repositoryKey>javascript</repositoryKey>
			<key>SingleQuote</key>
			<priority>MAJOR</priority>
		</rule>
		<rule>
			<repositoryKey>common-js</repositoryKey>
			<key>InsufficientCommentDensity</key>
			<priority>MAJOR</priority>
		</rule>
		<rule>
			<repositoryKey>common-js</repositoryKey>
			<key>DuplicatedBlocks</key>
			<priority>MAJOR</priority>
		</rule>
		<rule>
			<repositoryKey>common-js</repositoryKey>
			<key>InsufficientLineCoverage</key>
			<priority>MAJOR</priority>
		</rule>
		<rule>
			<repositoryKey>common-js</repositoryKey>
			<key>InsufficientBranchCoverage</key>
			<priority>MAJOR</priority>
		</rule>
	</rules>
</profile>